{
  "recentFiles": [
    {
      "basename": "_Welcome",
      "path": "20_Entry/_Welcome.md"
    },
    {
      "basename": "therapy",
      "path": "30_Topics/31_Stubs/therapy.md"
    },
    {
      "basename": "Self-hatred is born out of dissonance between self-image and self-perception",
      "path": "40_Evergreens/Self-hatred is born out of dissonance between self-image and self-perception.md"
    },
    {
      "basename": "JUSTEVERGREENS",
      "path": "JUSTEVERGREENS.md"
    },
    {
      "basename": "What is the cognitive effect of living in an unjust world",
      "path": "40_Evergreens/What is the cognitive effect of living in an unjust world.md"
    },
    {
      "basename": "Rise of Modern Conservatism",
      "path": "40_Evergreens/Rise of Modern Conservatism.md"
    },
    {
      "basename": "Ronald Reagan invented modern conservatism",
      "path": "40_Evergreens/Ronald Reagan invented modern conservatism.md"
    },
    {
      "basename": "EVERGREENS",
      "path": "20_Entry/EVERGREENS.md"
    },
    {
      "basename": "_INDEX",
      "path": "20_Entry/_INDEX.md"
    },
    {
      "basename": "Your anxiety knows your insecurities better than you do",
      "path": "40_Evergreens/Your anxiety knows your insecurities better than you do.md"
    },
    {
      "basename": "Autism",
      "path": "30_Topics/31_Stubs/Autism.md"
    },
    {
      "basename": "philosophy",
      "path": "30_Topics/31_Stubs/philosophy.md"
    },
    {
      "basename": "conceptual notes",
      "path": "30_Topics/31_Stubs/conceptual notes.md"
    },
    {
      "basename": "Your second brain should be frictionless access to a curated base of knowledge",
      "path": "40_Evergreens/Your second brain should be frictionless access to a curated base of knowledge.md"
    },
    {
      "basename": "bi-directional links",
      "path": "30_Topics/32_Terms/bi-directional links.md"
    },
    {
      "basename": "defense-mechanisms",
      "path": "30_Topics/32_Terms/defense-mechanisms.md"
    },
    {
      "basename": "KANBAN",
      "path": "20_Entry/KANBAN.md"
    },
    {
      "basename": "QUICKNOTE",
      "path": "20_Entry/QUICKNOTE.md"
    },
    {
      "basename": "RELATED-TOPICS",
      "path": "20_Entry/RELATED-TOPICS.md"
    },
    {
      "basename": "LAST-WEEK",
      "path": "20_Entry/LAST-WEEK.md"
    },
    {
      "basename": "EVERSPROUTS",
      "path": "20_Entry/EVERSPROUTS.md"
    },
    {
      "basename": "EVERSEEDS",
      "path": "20_Entry/EVERSEEDS.md"
    },
    {
      "basename": "TODO",
      "path": "20_Entry/TODO.md"
    },
    {
      "basename": "RECENTLY-MODIFIED",
      "path": "20_Entry/RECENTLY-MODIFIED.md"
    },
    {
      "basename": "File Sizes",
      "path": "20_Entry/File Sizes.md"
    },
    {
      "basename": "CONTENTNOTES",
      "path": "20_Entry/CONTENTNOTES.md"
    },
    {
      "basename": "_NOW",
      "path": "20_Entry/_NOW.md"
    },
    {
      "basename": "Templater",
      "path": "30_Topics/33_Tools/Templater.md"
    },
    {
      "basename": "Mermaid (software)",
      "path": "30_Topics/33_Tools/Mermaid (software).md"
    },
    {
      "basename": "neurodiversity",
      "path": "30_Topics/neurodiversity.md"
    },
    {
      "basename": "note writing",
      "path": "30_Topics/note writing.md"
    },
    {
      "basename": "self",
      "path": "30_Topics/self.md"
    },
    {
      "basename": "DrK Interviews",
      "path": "30_Topics/DrK Interviews.md"
    },
    {
      "basename": "@visakanv on Twitter",
      "path": "30_Topics/@visakanv on Twitter.md"
    },
    {
      "basename": "Psychology",
      "path": "30_Topics/Psychology.md"
    },
    {
      "basename": "Reagan",
      "path": "30_Topics/Reagan.md"
    },
    {
      "basename": "Develop Obsidian plugins",
      "path": "40_Evergreens/Develop Obsidian plugins.md"
    },
    {
      "basename": "sympathy",
      "path": "30_Topics/31_Stubs/sympathy.md"
    },
    {
      "basename": "the culture war",
      "path": "30_Topics/31_Stubs/the culture war.md"
    },
    {
      "basename": "Suicide",
      "path": "30_Topics/31_Stubs/Suicide.md"
    },
    {
      "basename": "transphobia",
      "path": "30_Topics/31_Stubs/transphobia.md"
    },
    {
      "basename": "unconditional love",
      "path": "30_Topics/31_Stubs/unconditional love.md"
    },
    {
      "basename": "white supremacy",
      "path": "30_Topics/31_Stubs/white supremacy.md"
    },
    {
      "basename": "women",
      "path": "30_Topics/31_Stubs/women.md"
    },
    {
      "basename": "worldview",
      "path": "30_Topics/31_Stubs/worldview.md"
    },
    {
      "basename": "ADHD",
      "path": "30_Topics/32_Terms/ADHD.md"
    },
    {
      "basename": "religion",
      "path": "30_Topics/religion.md"
    },
    {
      "basename": "DID (Dissociative Idenitty Disorder)",
      "path": "30_Topics/DID (Dissociative Idenitty Disorder).md"
    },
    {
      "basename": "Commits",
      "path": "20_Entry/Commits.md"
    },
    {
      "basename": "'Don't be the reason that rules exist' - Nathan Eloe",
      "path": "10_Sources/Personal/'Don't be the reason that rules exist' - Nathan Eloe.md"
    }
  ],
  "omittedPaths": [],
  "maxLength": null
}